{
  "version": 1,
  "assetType": "barraco barraco-5",
  "category": "favela",
  "density": "medium-high",
  "dominantHeight": "low-rise-irregular",
  "silhouette": {
    "primaryMassing": "clustered-lowrise",
    "roofProfile": "mixed-flat-and-patched",
    "heightProfile": "low-spread",
    "skyline": "broken-dense",
    "footprintProfile": "irregular-cluster",
    "detailPriority": [
      "telhados sobrepostos",
      "anexos",
      "escadas externas",
      "caixas d'agua",
      "adensamento"
    ]
  },
  "materials": [
    "concreto cru",
    "reboco gasto",
    "tijolo aparente",
    "telha metalica",
    "caixa d'agua",
    "lona",
    "metal remendado"
  ],
  "requiredModules": [
    "barraco-unit",
    "barraco-stacked",
    "barraco-corner",
    "barraco-roof-patch",
    "external-pipe",
    "corrugated-roof",
    "side-wall",
    "awning",
    "small-window",
    "stair"
  ],
  "forbiddenModules": [
    "stage",
    "truss",
    "cluster-core-dense",
    "speaker-stack"
  ],
  "composition": {
    "layout": "single-or-stacked-shelter",
    "primaryAxis": "front-left",
    "stacking": "loose",
    "streetPresence": "medium-low",
    "edgeNoise": "medium",
    "anchorMass": "center",
    "layering": [
      "core-volume",
      "roof",
      "access",
      "utility"
    ],
    "variationPriority": [
      "roof-patch",
      "pipe-side",
      "awning-front"
    ]
  },
  "styleGuide": {
    "profile": "cs-rio-semirealista",
    "resolvedProfile": "dense-favela",
    "family": "barraco",
    "perspective": "isometric-2:1",
    "paletteIntent": null,
    "compositionPolicy": {
      "layout": "single-shelter-plus-annex",
      "baseAnchor": {
        "x": 94,
        "y": 126
      },
      "columns": 2,
      "xStep": 20,
      "yStep": 6,
      "rowLift": 10,
      "layerPattern": [
        "foreground",
        "foreground",
        "midground",
        "midground",
        "background",
        "overlay"
      ]
    },
    "modulePolicy": {
      "targetNodeCount": 6,
      "primaryModules": [
        "barraco-unit",
        "barraco-stacked",
        "barraco-corner"
      ],
      "secondaryModules": [
        "barraco-roof-patch",
        "corrugated-roof",
        "side-wall"
      ],
      "detailModules": [
        "external-pipe",
        "awning",
        "small-window",
        "stair"
      ],
      "forbiddenModules": [
        "stage",
        "truss",
        "cluster-core-dense",
        "speaker-stack"
      ]
    },
    "variationPolicy": {
      "jitter": {
        "x": 5,
        "y": 4
      },
      "scale": {
        "min": 0.97,
        "max": 1.06
      },
      "roofVariation": "high",
      "materialVariation": "medium-high",
      "attachmentVariation": "medium"
    },
    "visualRules": [
      "preservar leitura improvisada do volume",
      "não virar cubo genérico limpo",
      "cobertura e anexos precisam dominar a silhueta"
    ]
  },
  "nodes": [
    {
      "id": "barraco-unit-1",
      "module": "barraco-unit",
      "layer": "foreground",
      "anchor": {
        "x": 94,
        "y": 126
      },
      "heightTier": "primary",
      "variationSeed": 1,
      "children": []
    },
    {
      "id": "barraco-stacked-2",
      "module": "barraco-stacked",
      "layer": "foreground",
      "anchor": {
        "x": 114,
        "y": 120
      },
      "heightTier": "primary",
      "variationSeed": 2,
      "children": []
    },
    {
      "id": "barraco-corner-3",
      "module": "barraco-corner",
      "layer": "midground",
      "anchor": {
        "x": 94,
        "y": 116
      },
      "heightTier": "secondary",
      "variationSeed": 3,
      "children": []
    },
    {
      "id": "barraco-roof-patch-4",
      "module": "barraco-roof-patch",
      "layer": "midground",
      "anchor": {
        "x": 114,
        "y": 110
      },
      "heightTier": "secondary",
      "variationSeed": 4,
      "children": []
    },
    {
      "id": "corrugated-roof-5",
      "module": "corrugated-roof",
      "layer": "background",
      "anchor": {
        "x": 94,
        "y": 106
      },
      "heightTier": "detail",
      "variationSeed": 5,
      "children": []
    },
    {
      "id": "side-wall-6",
      "module": "side-wall",
      "layer": "overlay",
      "anchor": {
        "x": 114,
        "y": 100
      },
      "heightTier": "detail",
      "variationSeed": 6,
      "children": []
    }
  ]
}
