{
  "version": 1,
  "assetType": "dock-industrial docas",
  "category": "factory",
  "density": "medium-low",
  "dominantHeight": "low-rise-horizontal",
  "silhouette": {
    "primaryMassing": "industrial-complex",
    "roofProfile": "shed-and-flat-mix",
    "heightProfile": "low-bulk-with-utility-elements",
    "skyline": "chimney-crane-or-piles",
    "footprintProfile": "wide-industrial",
    "detailPriority": [
      "galpao",
      "doca",
      "sucata ou equipamento",
      "portao",
      "anexo tecnico"
    ]
  },
  "materials": [
    "galpao",
    "concreto",
    "metal",
    "chamine",
    "doca de carga",
    "doca"
  ],
  "requiredModules": [
    "anchor-shadow",
    "dock-warehouse",
    "container-stack"
  ],
  "forbiddenModules": [
    "stage",
    "hospital-entry",
    "house-simple-core"
  ],
  "composition": {
    "layout": "industrial-complex",
    "primaryAxis": "front-left",
    "stacking": "balanced",
    "streetPresence": "medium",
    "edgeNoise": "medium",
    "anchorMass": "center-left",
    "layering": [
      "main-volume",
      "secondary-volume",
      "roof",
      "detail"
    ],
    "variationPriority": [
      "height",
      "roof",
      "attachments"
    ]
  },
  "styleGuide": {
    "profile": "cs-rio-semirealista",
    "resolvedProfile": "simcity-urban",
    "family": "dock-industrial",
    "perspective": "isometric-2:1",
    "paletteIntent": null,
    "compositionPolicy": {
      "layout": "dock-yard",
      "baseAnchor": {
        "x": 92,
        "y": 126
      },
      "columns": 2,
      "xStep": 14,
      "yStep": 4,
      "rowLift": 8,
      "layerPattern": [
        "foreground",
        "midground",
        "background",
        "overlay"
      ]
    },
    "modulePolicy": {
      "targetNodeCount": 4,
      "primaryModules": [
        "dock-warehouse"
      ],
      "secondaryModules": [
        "container-stack"
      ],
      "detailModules": [],
      "forbiddenModules": [
        "stage",
        "hospital-entry",
        "house-simple-core"
      ]
    },
    "variationPolicy": {
      "jitter": {
        "x": 3,
        "y": 2
      },
      "scale": {
        "min": 0.98,
        "max": 1.04
      },
      "roofVariation": "medium",
      "materialVariation": "medium",
      "attachmentVariation": "medium"
    },
    "visualRules": [
      "precisa sugerir patio industrial e carga",
      "containers e braços de carga ajudam a leitura de doca"
    ]
  },
  "nodes": [
    {
      "id": "dock-warehouse-1",
      "module": "dock-warehouse",
      "layer": "foreground",
      "anchor": {
        "x": 92,
        "y": 126
      },
      "heightTier": "primary",
      "variationSeed": 1,
      "children": []
    },
    {
      "id": "container-stack-2",
      "module": "container-stack",
      "layer": "midground",
      "anchor": {
        "x": 106,
        "y": 122
      },
      "heightTier": "primary",
      "variationSeed": 2,
      "children": []
    },
    {
      "id": "anchor-shadow-3",
      "module": "anchor-shadow",
      "layer": "background",
      "anchor": {
        "x": 92,
        "y": 118
      },
      "heightTier": "secondary",
      "variationSeed": 3,
      "children": []
    },
    {
      "id": "dock-warehouse-4",
      "module": "dock-warehouse",
      "layer": "overlay",
      "anchor": {
        "x": 106,
        "y": 114
      },
      "heightTier": "secondary",
      "variationSeed": 4,
      "children": []
    }
  ]
}
